jsonschema_codegen/__init__.py
jsonschema_codegen/__main__.py
jsonschema_codegen/_interpreters.py
jsonschema_codegen/_version.py
jsonschema_codegen/compiler.py
jsonschema_codegen/exceptions.py
jsonschema_codegen/exprs.py
jsonschema_codegen/generator.py
jsonschema_codegen/parsers.py
jsonschema_codegen/py.typed
jsonschema_codegen/renderers.py
jsonschema_codegen/resolvers.py
jsonschema_codegen/schema.py
jsonschema_codegen/types.py
jsonschema_codegen_py-0.0.1.dist-info/METADATA
jsonschema_codegen_py-0.0.1.dist-info/WHEEL
jsonschema_codegen_py-0.0.1.dist-info/licenses/LICENSE
jsonschema_codegen_py-0.0.1.dist-info/RECORD
